holoviz/.version
holoviz/__init__.py
holoviz/__main__.py
holoviz/examples/datasets.yml
holoviz/examples/assets/altair.png
holoviz/examples/assets/bokeh.png
holoviz/examples/assets/bokeh_logo.svg
holoviz/examples/assets/cartopy.png
holoviz/examples/assets/colorcet.png
holoviz/examples/assets/dask.png
holoviz/examples/assets/dask.svg
holoviz/examples/assets/datashader.png
holoviz/examples/assets/datashader_pipeline.png
holoviz/examples/assets/ds_hv_bokeh.png
holoviz/examples/assets/ds_hv_bokeh2.png
holoviz/examples/assets/earthquakes.png
holoviz/examples/assets/geopandas.png
holoviz/examples/assets/geoviews.png
holoviz/examples/assets/ggplot2.png
holoviz/examples/assets/graphviz.png
holoviz/examples/assets/header_logo.png
holoviz/examples/assets/holoviews.png
holoviz/examples/assets/holoviz-logo-stacked.svg
holoviz/examples/assets/holoviz-logo-unstacked.svg
holoviz/examples/assets/hv+bk.png
holoviz/examples/assets/hv_gv_bk_ds_pa.png
holoviz/examples/assets/hvplot.png
holoviz/examples/assets/intake.png
holoviz/examples/assets/iris.png
holoviz/examples/assets/jupyter.png
holoviz/examples/assets/landscape_hv_nx.png
holoviz/examples/assets/landscape_hv_nx_panel.png
holoviz/examples/assets/landscape_hv_nx_pyviz.png
holoviz/examples/assets/matplotlib_logo.png
holoviz/examples/assets/matplotlib_wm.png
holoviz/examples/assets/networkx.png
holoviz/examples/assets/numba.png
holoviz/examples/assets/numpy.png
holoviz/examples/assets/pandas.png
holoviz/examples/assets/panel.png
holoviz/examples/assets/param.png
holoviz/examples/assets/pillow.png
holoviz/examples/assets/plotly.png
holoviz/examples/assets/plotnine.png
holoviz/examples/assets/pn_hp_hv_gv_ds_pa_cs.png
holoviz/examples/assets/pn_hv_gv_bk_ds_pa.png
holoviz/examples/assets/scipy.png
holoviz/examples/assets/seaborn.png
holoviz/examples/assets/shortcuts.png
holoviz/examples/assets/sympy.png
holoviz/examples/assets/tutorial_app.gif
holoviz/examples/assets/usgs_logo.png
holoviz/examples/assets/vega.png
holoviz-0.11.6.dist-info/LICENSE.txt
holoviz-0.11.6.dist-info/METADATA
holoviz-0.11.6.dist-info/WHEEL
holoviz-0.11.6.dist-info/entry_points.txt
holoviz-0.11.6.dist-info/top_level.txt
holoviz-0.11.6.dist-info/RECORD
