Metadata-Version: 2.1
Name: holoviz
Version: 0.11.6
Summary: High-level tools to simplify visualization in Python.
Home-page: http://holoviz.org
Author: HoloViz developers
Author-email: developers@holoviz.org
Maintainer: HoloViz developers
Maintainer-email: developers@holoviz.org
License: BSD 3-Clause License
Project-URL: Bug Tracker, https://github.com/holoviz/holoviz/issues
Project-URL: Documentation, http://holoviz.org
Project-URL: Source Code, https://github.com/holoviz/holoviz
Platform: UNKNOWN
Classifier: License :: OSI Approved :: BSD License
Classifier: Operating System :: OS Independent
Classifier: Programming Language :: Python
Classifier: Programming Language :: Python :: 3.7
Classifier: Development Status :: 5 - Production/Stable
Classifier: Intended Audience :: Science/Research
Classifier: Intended Audience :: Developers
Classifier: Natural Language :: English
Classifier: Topic :: Scientific/Engineering
Requires-Python: >=3.6
Requires-Dist: numpy (==1.18.1)
Requires-Dist: pandas (==1.0.3)
Requires-Dist: dask[complete] (==2.17.2)
Requires-Dist: xarray (==0.15.1)
Requires-Dist: matplotlib (==3.1.3)
Requires-Dist: notebook (>=5.5)
Requires-Dist: rise
Requires-Dist: bokeh (<2.1,>=2.0.1)
Requires-Dist: holoviews (<1.14.0,>=1.13.2)
Requires-Dist: hvplot (<0.7.0,>=0.6.0)
Requires-Dist: datashader (<0.12.0,>=0.11.0)
Requires-Dist: panel (<1.0,>=0.9.5)
Requires-Dist: param (<2.0.0,>=1.9.2)
Requires-Dist: pyct[cmd]
Provides-Extra: doc
Requires-Dist: nbsite (>=0.6.1) ; extra == 'doc'
Requires-Dist: sphinx-holoviz-theme ; extra == 'doc'
Provides-Extra: indirect
Requires-Dist: netcdf4 ; extra == 'indirect'
Requires-Dist: fastparquet (>=0.2.1) ; extra == 'indirect'
Requires-Dist: python-snappy ; extra == 'indirect'
Provides-Extra: tests
Requires-Dist: nbsmoke (>=0.2.6) ; extra == 'tests'
Requires-Dist: flake8 ; extra == 'tests'
Requires-Dist: pytest (>=2.8.5) ; extra == 'tests'
